README.txt
bootstrap.py
buildout.cfg
setup.py
docs/HISTORY.txt
rpatterson/__init__.py
rpatterson.listfile.egg-info/PKG-INFO
rpatterson.listfile.egg-info/SOURCES.txt
rpatterson.listfile.egg-info/dependency_links.txt
rpatterson.listfile.egg-info/entry_points.txt
rpatterson.listfile.egg-info/namespace_packages.txt
rpatterson.listfile.egg-info/not-zip-safe
rpatterson.listfile.egg-info/requires.txt
rpatterson.listfile.egg-info/top_level.txt
rpatterson/listfile/README.txt
rpatterson/listfile/__init__.py
rpatterson/listfile/tests.py