Metadata-Version: 1.0
Name: rpatterson.listfile
Version: 0.1
Summary: Support list operations over lines of file-like objects
Home-page: http://pypi.python.org/pypi/rpatterson.listfile
Author: Ross Patterson
Author-email: me@rpatterson.net
License: GPL
Platform: UNKNOWN
Classifier: Programming Language :: Python
Classifier: Topic :: Software Development :: Libraries :: Python Modules
